spooler
tests
