Metadata-Version: 1.1
Name: pyspooler
Version: 0.1.2
Summary: Python spooler
Home-page: https://github.com/Shir0kamii/pyspooler
Author: Shir0kamii
Author-email: shir0kamii@gmail.com
License: UNKNOWN
Download-URL: https://github.com/Shir0kamii/pyspooler/tags
Platform: any
Classifier: Programming Language :: Python
Classifier: Programming Language :: Python :: 3
Classifier: Programming Language :: Python :: 3.4
Classifier: Programming Language :: Python :: 3.5
Classifier: Topic :: Software Development :: Libraries :: Python Modules
